FAQRobot/QQ.py
FAQRobot/__init__.py
FAQRobot/utils.py
FAQRobot-0.0.3.dist-info/LICENSE
FAQRobot-0.0.3.dist-info/METADATA
FAQRobot-0.0.3.dist-info/WHEEL
FAQRobot-0.0.3.dist-info/top_level.txt
FAQRobot-0.0.3.dist-info/RECORD
