Metadata-Version: 2.1
Name: FAQRobot
Version: 0.0.3
Summary: guoruili markdown editor
Home-page: https://markdown.felinae.net
Author: guoruili
Author-email: guoruili@mail.emotibot.com
License: UNKNOWN
Keywords: FAQRobot markdown editor editormd
Platform: UNKNOWN
